{
  "version": "5.0.1",
  "flags": {},
  "shapes": [
    {
      "label": "plane",
      "points": [
        [
          903.2164948453609,
          650.5670103092784
        ],
        [
          931.0515463917526,
          670.1546391752578
        ]
      ],
      "group_id": null,
      "shape_type": "rectangle",
      "flags": {}
    },
    {
      "label": "plane",
      "points": [
        [
          973.319587628866,
          641.2886597938144
        ],
        [
          998.0618556701031,
          660.8762886597939
        ]
      ],
      "group_id": null,
      "shape_type": "rectangle",
      "flags": {}
    },
    {
      "label": "plane",
      "points": [
        [
          1084.659793814433,
          626.8556701030928
        ],
        [
          1105.278350515464,
          646.4432989690722
        ]
      ],
      "group_id": null,
      "shape_type": "rectangle",
      "flags": {}
    },
    {
      "label": "plane",
      "points": [
        [
          1113.5257731958764,
          645.4123711340206
        ],
        [
          1142.3917525773197,
          661.9072164948453
        ]
      ],
      "group_id": null,
      "shape_type": "rectangle",
      "flags": {}
    },
    {
      "label": "plane",
      "points": [
        [
          937.2371134020619,
          460.8762886597939
        ],
        [
          991.8762886597939,
          487.680412371134
        ]
      ],
      "group_id": null,
      "shape_type": "rectangle",
      "flags": {}
    },
    {
      "label": "plane",
      "points": [
        [
          1000.1237113402062,
          449.5360824742269
        ],
        [
          1048.5773195876288,
          481.4948453608248
        ]
      ],
      "group_id": null,
      "shape_type": "rectangle",
      "flags": {}
    },
    {
      "label": "plane",
      "points": [
        [
          1090.8453608247423,
          492.8350515463918
        ],
        [
          1138.2680412371135,
          514.4845360824743
        ]
      ],
      "group_id": null,
      "shape_type": "rectangle",
      "flags": {}
    },
    {
      "label": "plane",
      "points": [
        [
          1152.701030927835,
          483.5567010309279
        ],
        [
          1200.1237113402062,
          507.2680412371134
        ]
      ],
      "group_id": null,
      "shape_type": "rectangle",
      "flags": {}
    },
    {
      "label": "plane",
      "points": [
        [
          1100.3194888178914,
          458.14696485623006
        ],
        [
          1132.9073482428116,
          477.31629392971246
        ]
      ],
      "group_id": null,
      "shape_type": "rectangle",
      "flags": {}
    },
    {
      "label": "plane",
      "points": [
        [
          1143.7699680511182,
          466.45367412140575
        ],
        [
          1175.3993610223642,
          482.7476038338658
        ]
      ],
      "group_id": null,
      "shape_type": "rectangle",
      "flags": {}
    },
    {
      "label": "plane",
      "points": [
        [
          1185.9424920127797,
          473.8019169329074
        ],
        [
          1215.6549520766773,
          490.4153354632588
        ]
      ],
      "group_id": null,
      "shape_type": "rectangle",
      "flags": {}
    },
    {
      "label": "plane",
      "points": [
        [
          1230.0319488817893,
          484.9840255591055
        ],
        [
          1259.744408945687,
          499.68051118210866
        ]
      ],
      "group_id": null,
      "shape_type": "rectangle",
      "flags": {}
    },
    {
      "label": "plane",
      "points": [
        [
          264.53674121405754,
          519.4888178913739
        ],
        [
          296.4856230031949,
          539.9361022364218
        ]
      ],
      "group_id": null,
      "shape_type": "rectangle",
      "flags": {}
    },
    {
      "label": "plane",
      "points": [
        [
          307.98722044728436,
          517.2523961661342
        ],
        [
          334.8242811501598,
          535.4632587859425
        ]
      ],
      "group_id": null,
      "shape_type": "rectangle",
      "flags": {}
    },
    {
      "label": "plane",
      "points": [
        [
          294.88817891373805,
          482.7476038338658
        ],
        [
          318.84984025559106,
          495.5271565495208
        ]
      ],
      "group_id": null,
      "shape_type": "rectangle",
      "flags": {}
    },
    {
      "label": "plane",
      "points": [
        [
          325.8785942492013,
          488.49840255591056
        ],
        [
          351.4376996805112,
          501.91693290734827
        ]
      ],
      "group_id": null,
      "shape_type": "rectangle",
      "flags": {}
    },
    {
      "label": "plane",
      "points": [
        [
          352.07667731629397,
          492.65175718849844
        ],
        [
          377.63578274760386,
          505.75079872204475
        ]
      ],
      "group_id": null,
      "shape_type": "rectangle",
      "flags": {}
    },
    {
      "label": "plane",
      "points": [
        [
          368.370607028754,
          474.7603833865815
        ],
        [
          393.2907348242812,
          487.5399361022364
        ]
      ],
      "group_id": null,
      "shape_type": "rectangle",
      "flags": {}
    },
    {
      "label": "plane",
      "points": [
        [
          389.77635782747603,
          477.95527156549525
        ],
        [
          415.6549520766773,
          490.73482428115017
        ]
      ],
      "group_id": null,
      "shape_type": "rectangle",
      "flags": {}
    },
    {
      "label": "plane",
      "points": [
        [
          425.8785942492013,
          483.70607028753994
        ],
        [
          451.11821086261983,
          498.7220447284345
        ]
      ],
      "group_id": null,
      "shape_type": "rectangle",
      "flags": {}
    },
    {
      "label": "plane",
      "points": [
        [
          433.54632587859425,
          465.1757188498403
        ],
        [
          453.67412140575084,
          478.594249201278
        ]
      ],
      "group_id": null,
      "shape_type": "rectangle",
      "flags": {}
    },
    {
      "label": "plane",
      "points": [
        [
          452.07667731629397,
          468.370607028754
        ],
        [
          472.2044728434505,
          482.7476038338658
        ]
      ],
      "group_id": null,
      "shape_type": "rectangle",
      "flags": {}
    },
    {
      "label": "plane",
      "points": [
        [
          470.926517571885,
          472.2044728434505
        ],
        [
          495.5271565495208,
          486.26198083067095
        ]
      ],
      "group_id": null,
      "shape_type": "rectangle",
      "flags": {}
    },
    {
      "label": "plane",
      "points": [
        [
          508.30670926517575,
          454.9520766773163
        ],
        [
          526.8370607028754,
          467.7316293929713
        ]
      ],
      "group_id": null,
      "shape_type": "rectangle",
      "flags": {}
    },
    {
      "label": "plane",
      "points": [
        [
          526.517571884984,
          458.4664536741214
        ],
        [
          551.4376996805112,
          473.8019169329074
        ]
      ],
      "group_id": null,
      "shape_type": "rectangle",
      "flags": {}
    },
    {
      "label": "plane",
      "points": [
        [
          561.0223642172524,
          462.30031948881793
        ],
        [
          586.5814696485623,
          477.31629392971246
        ]
      ],
      "group_id": null,
      "shape_type": "rectangle",
      "flags": {}
    },
    {
      "label": "plane",
      "points": [
        [
          587.8594249201278,
          469.32907348242816
        ],
        [
          611.5015974440895,
          482.7476038338658
        ]
      ],
      "group_id": null,
      "shape_type": "rectangle",
      "flags": {}
    },
    {
      "label": "plane",
      "points": [
        [
          570.6070287539936,
          477.63578274760386
        ],
        [
          599.3610223642173,
          494.56869009584665
        ]
      ],
      "group_id": null,
      "shape_type": "rectangle",
      "flags": {}
    }
  ],
  "imagePath": "train_S729-02_0029.jpg",
  "imageData": null,
  "imageHeight": 1080,
  "imageWidth": 1920
}